PyUtilToolKit/__init__.py
PyUtilToolKit/log.py
PyUtilToolKit/my_requests.py
PyUtilToolKit/pathSetting.py
PyUtilToolKit/recursion.py
PyUtilToolKit/asserts/__init__.py
PyUtilToolKit/asserts/assert_base.py
PyUtilToolKit/asserts/res_assert.py
PyUtilToolKitDev/__init__.py
PyUtilToolKitDev/base_tool.py
PyUtilToolKitDev/convert_file.py
PyUtilToolKitDev/encrypt.py
PyUtilToolKitDev/faker_util.py
PyUtilToolKitDev/host_env.py
PyUtilToolKitDev/hypothesis_data.py
PyUtilToolKitDev/log.py
PyUtilToolKitDev/login_base.py
PyUtilToolKitDev/my_requests.py
PyUtilToolKitDev/operation_cash.py
PyUtilToolKitDev/operation_json.py
PyUtilToolKitDev/pathSetting.py
PyUtilToolKitDev/recursion.py
PyUtilToolKitDev/touch_csv.py
PyUtilToolKitDev/touch_file.py
PyUtilToolKitDev/asserts/__init__.py
PyUtilToolKitDev/asserts/assert_base.py
PyUtilToolKitDev/asserts/res_assert.py
PyUtilToolKitDev/database/__init__.py
PyUtilToolKitDev/database/databaseScript/__init__.py
PyUtilToolKitDev/database/databaseScript/xuanHu_databaseScript/__init__.py
PyUtilToolKitDev/database/databaseScript/xuanHu_databaseScript/xuanHuDataBaseScript.py
PyUtilToolKitDev/database/databaseScript/yunYaoKe_databaseScript/__init__.py
PyUtilToolKitDev/database/database_design/__init__.py
PyUtilToolKitDev/database/database_design/database_base.py
PyUtilToolKitDev/database/database_design/database_insert.py
PyUtilToolKitDev/database/database_design/database_listen.py
PyUtilToolKitDev/database/database_design/database_table.py
PyUtilToolKitDev/install_tool/__init__.py
PyUtilToolKitDev/install_tool/install_requirements.py
PyUtilToolKitDev/notify/__init__.py
PyUtilToolKitDev/notify/aLiMail.py
PyUtilToolKitDev/notify/notice.py
PyUtilToolKitDev/notify/report.py
PyUtilToolKit-1.0.8.dist-info/METADATA
PyUtilToolKit-1.0.8.dist-info/WHEEL
PyUtilToolKit-1.0.8.dist-info/top_level.txt
PyUtilToolKit-1.0.8.dist-info/RECORD
